recsim/__init__.py
recsim/agent.py
recsim/agent_test.py
recsim/choice_model.py
recsim/choice_model_test.py
recsim/document.py
recsim/main.py
recsim/user.py
recsim/utils.py
recsim/utils_test.py
recsim/agents/__init__.py
recsim/agents/agent_utils.py
recsim/agents/cluster_bandit_agent.py
recsim/agents/cluster_bandit_agent_test.py
recsim/agents/greedy_pctr_agent.py
recsim/agents/greedy_pctr_agent_test.py
recsim/agents/random_agent.py
recsim/agents/random_agent_test.py
recsim/agents/tabular_q_agent.py
recsim/agents/tabular_q_agent_test.py
recsim/agents/ucb1_agent_test.py
recsim/agents/bandits/__init__.py
recsim/agents/bandits/algorithms.py
recsim/agents/bandits/algorithms_test.py
recsim/agents/bandits/glm_algorithms.py
recsim/agents/bandits/glm_algorithms_test.py
recsim/agents/layers/__init__.py
recsim/agents/layers/abstract_click_bandit.py
recsim/agents/layers/cluster_click_statistics.py
recsim/agents/layers/cluster_click_statistics_test.py
recsim/agents/layers/fixed_length_history.py
recsim/agents/layers/fixed_length_history_test.py
recsim/agents/layers/sufficient_statistics.py
recsim/agents/layers/temporal_aggregation.py
recsim/environments/__init__.py
recsim/environments/interest_evolution.py
recsim/environments/interest_evolution_test.py
recsim/environments/interest_exploration.py
recsim/environments/interest_exploration_test.py
recsim/environments/long_term_satisfaction.py
recsim/simulator/__init__.py
recsim/simulator/environment.py
recsim/simulator/environment_test.py
recsim/simulator/recsim_gym.py
recsim/simulator/runner_lib.py
recsim_no_tf-0.2.3.dist-info/LICENSE
recsim_no_tf-0.2.3.dist-info/METADATA
recsim_no_tf-0.2.3.dist-info/WHEEL
recsim_no_tf-0.2.3.dist-info/top_level.txt
recsim_no_tf-0.2.3.dist-info/RECORD
