Metadata-Version: 2.1
Name: recsim-no-tf
Version: 0.2.3
Summary: RecSim: A Configurable Recommender Systems Simulation Platform (w/o Tensorflow deps)
Home-page: https://github.com/kittipatv/recsim-no-tf
Author: The RecSim Team, Kittipat Virochsiri
Author-email: kittipatv@users.noreply.github.com
License: Apache 2.0
Project-URL: Documentation, https://github.com/kittipatv/recsim-no-tf
Project-URL: Bug Reports, https://github.com/kittipatv/recsim-no-tf/issues
Project-URL: Source, https://github.com/kittipatv/recsim-no-tf
Keywords: recsim reinforcement-learning recommender-system simulation
Platform: UNKNOWN
Classifier: Development Status :: 3 - Alpha
Classifier: Intended Audience :: Developers
Classifier: Intended Audience :: Education
Classifier: Intended Audience :: Science/Research
Classifier: License :: OSI Approved :: Apache Software License
Classifier: Programming Language :: Python :: 2
Classifier: Programming Language :: Python :: 3
Classifier: Topic :: Scientific/Engineering
Classifier: Topic :: Scientific/Engineering :: Mathematics
Classifier: Topic :: Scientific/Engineering :: Artificial Intelligence
Classifier: Topic :: Software Development
Classifier: Topic :: Software Development :: Libraries
Classifier: Topic :: Software Development :: Libraries :: Python Modules
Requires-Dist: absl-py
Requires-Dist: gin-config
Requires-Dist: gym
Requires-Dist: numpy
Requires-Dist: scipy
